text_extractor/__init__.py
text_extractor/main_extractor.py
text_extractor/utils.py
text_extractor/extractors/__init__.py
text_extractor/extractors/pdf_extractor.py
text_extractor/extractors/txt_extractor.py
text_extractor-0.0.2.dist-info/METADATA
text_extractor-0.0.2.dist-info/WHEEL
text_extractor-0.0.2.dist-info/top_level.txt
text_extractor-0.0.2.dist-info/RECORD
