Metadata-Version: 2.1
Name: text-extractor
Version: 0.0.2
Summary: Text extracting package from multiple file formats
Home-page: UNKNOWN
Author: Lee Ying Yang
Author-email: overaneout@gmail.com
License: Apache Software License (Apache License 2.0)
Platform: UNKNOWN
Requires-Python: >=3.6
Requires-Dist: pdfminer.six (>=20200124)
